{
	"easy": [{"puzzle": [[1, 0, 8, 6, 0, 0, 3, 0, 0], [9, 0, 6, 0, 0, 0, 0, 0, 5], [7, 0, 0, 1, 0, 0, 0, 0, 0], [0, 8, 1, 0, 0, 0, 0, 5, 4], [0, 9, 7, 0, 0, 6, 2, 0, 3], [0, 0, 0, 5, 0, 0, 6, 7, 1], [4, 0, 3, 9, 6, 2, 0, 0, 0], [0, 0, 0, 7, 8, 0, 4, 0, 6], [0, 0, 5, 3, 0, 1, 0, 0, 2]], "clues": 35, "id": 8957828083690533816}, {"puzzle": [[3, 0, 0, 0, 0, 0, 0, 0, 0], [0, 0, 0, 0, 0, 3, 7, 0, 2], [9, 0, 2, 0, 8, 5, 0, 1, 0], [0, 2, 0, 3, 0, 0, 0, 0, 5], [6, 3, 0, 5, 7, 0, 2, 0, 0], [0, 9, 5, 0, 0, 6, 4, 3, 0], [7, 1, 0, 0, 0, 2, 9, 0, 0], [0, 0, 0, 1, 6, 0, 0, 0, 0], [2, 8, 6, 4, 3, 0, 0, 7, 1]], "clues": 35, "id": 562006569157511301}, {"puzzle": [[0, 6, 1, 0, 3, 8, 0, 5, 9], [4, 9, 5, 0, 2, 0, 0, 0, 0], [7, 0, 0, 4, 0, 5, 2, 0, 1], [0, 5, 0, 0, 0, 0, 7, 0, 2], [0, 0, 3, 0, 0, 4, 1, 0, 0], [1, 7, 9, 0, 8, 0, 6, 4, 3], [0, 0, 2, 3, 0, 0, 9, 0, 0], [0, 0, 7, 8, 0, 0, 0, 0, 6], [0, 4, 0, 0, 0, 0, 0, 0, 0]], "clues": 35, "id": -5606426822924447774}, {"puzzle": [[4, 0, 0, 0, 0, 3, 0, 1, 9], [3, 9, 8, 0, 0, 0, 0, 0, 5], [0, 0, 7, 9, 0, 0, 3, 0, 2], [6, 7, 0, 4, 0, 5, 2, 3, 0], [0, 5, 4, 2, 0, 0, 0, 9, 6], [0, 3, 0, 0, 0, 0, 5, 0, 0], [5, 0, 0, 0, 0, 0, 0, 0, 0], [9, 1, 2, 0, 4, 6, 8, 0, 0], [0, 8, 0, 5, 0, 0, 6, 0, 0]], "clues": 35, "id": -4988019617798708962}, {"puzzle": [[0, 0, 0, 0, 4, 0, 1, 3, 8], [8, 0, 1, 0, 0, 0, 0, 0, 9], [0, 4, 0, 0, 1, 8, 0, 0, 0], [6, 0, 3, 0, 8, 0, 9, 2, 1], [1, 5, 0, 0, 0, 0, 0, 6, 7], [0, 0, 4, 7, 0, 1, 8, 0, 0], [0, 8, 0, 1, 0, 0, 7, 9, 0], [5, 0, 0, 0, 7, 6, 0, 0, 0], [9, 3, 0, 0, 5, 0, 0, 0, 6]], "clues": 35, "id": 20286362369717563}, {"puzzle": [[0, 0, 6, 7, 0, 0, 0, 0, 8], [0, 0, 1, 6, 9, 0, 0, 0, 0], [8, 0, 4, 0, 5, 0, 0, 2, 0], [0, 1, 0, 9, 0, 0, 0, 0, 2], [0, 2, 8, 5, 3, 6, 0, 7, 1], [0, 6, 7, 0, 4, 0, 0, 0, 0], [7, 8, 0, 0, 0, 5, 0, 0, 3], [0, 0, 3, 0, 6, 0, 5, 0, 0], [0, 5, 0, 3, 7, 9, 1, 0, 0]], "clues": 35, "id": 4615981308645092565}, {"puzzle": [[9, 5, 0, 6, 0, 0, 0, 4, 0], [0, 4, 2, 0, 9, 0, 7, 0, 6], [6, 1, 7, 0, 3, 0, 0, 0, 2], [0, 0, 0, 0, 0, 4, 0, 6, 3], [0, 7, 0, 0, 0, 0, 4, 1, 0], [4, 0, 0, 0, 1, 3, 5, 0, 7], [0, 0, 0, 0, 0, 0, 0, 2, 9], [0, 0, 9, 0, 0, 0, 1, 0, 4], [8, 2, 1, 0, 4, 9, 0, 0, 0]], "clues": 35, "id": 4027609952855995629}, {"puzzle": [[0, 0, 0, 0, 0, 0, 1, 4, 8], [8, 0, 1, 0, 0, 0, 0, 0, 5], [0, 0, 5, 8, 0, 1, 0, 0, 7], [1, 2, 0, 5, 8, 0, 0, 0, 9], [0, 0, 0, 0, 7, 2, 8, 1, 0], [0, 0, 8, 0, 1, 0, 5, 3, 0], [7, 1, 0, 0, 0, 0, 0, 0, 0], [4, 0, 0, 0, 6, 5, 0, 9, 3], [0, 5, 0, 7, 0, 4, 2, 8, 0]], "clues": 35, "id": 4244033639405606979}, {"puzzle": [[3, 0, 5, 2, 0, 9, 1, 0, 0], [1, 0, 6, 8, 0, 0, 7, 0, 9], [8, 0, 9, 0, 0, 0, 5, 0, 3], [0, 0, 2, 5, 0, 1, 0, 0, 4], [0, 8, 0, 6, 0, 4, 3, 9, 0], [0, 6, 0, 0, 0, 0, 0, 0, 1], [4, 0, 3, 0, 0, 2, 0, 1, 7], [0, 0, 0, 0, 1, 3, 4, 0, 0], [0, 0, 0, 0, 0, 0, 9, 0, 2]], "clues": 35, "id": 2037212172697599535}, {"puzzle": [[0, 0, 2, 8, 9, 0, 0, 1, 6], [9, 0, 1, 4, 5, 0, 0, 0, 0], [0, 8, 0, 1, 0, 0, 5, 0, 2], [6, 3, 8, 5, 0, 0, 7, 0, 0], [0, 0, 0, 3, 0, 4, 2, 6, 5], [0, 0, 5, 0, 0, 6, 0, 0, 0], [5, 0, 0, 0, 3, 0, 8, 0, 1], [0, 0, 0, 0, 0, 0, 9, 0, 4], [0, 0, 0, 0, 4, 5, 6, 0, 3]], "clues": 35, "id": -4322886872181573197}, {"puzzle": [[6, 5, 9, 0, 0, 0, 0, 8, 1], [0, 1, 3, 8, 9, 4, 0, 2, 0], [0, 0, 0, 0, 0, 0, 7, 9, 3], [0, 0, 0, 0, 4, 0, 0, 0, 8], [0, 0, 0, 3, 0, 0, 0, 0, 0], [0, 3, 1, 0, 0, 0, 5, 0, 0], [0, 0, 0, 5, 6, 0, 8, 7, 9], [3, 6, 7, 9, 0, 8, 0, 0, 0], [5, 0, 8, 0, 7, 0, 3, 0, 2]], "clues": 35, "id": -6192570635448060784}, {"puzzle": [[5, 2, 0, 6, 0, 3, 0, 9, 0], [6, 9, 0, 0, 7, 0, 2, 0, 0], [0, 7, 4, 2, 9, 8, 0, 0, 6], [0, 0, 0, 3, 0, 0, 7, 5, 9], [0, 0, 0, 0, 0, 0, 4, 0, 0], [9, 3, 0, 0, 0, 0, 0, 1, 2], [0, 4, 0, 0, 0, 6, 3, 0, 5], [0, 6, 5, 8, 0, 4, 0, 0, 1], [0, 0, 0, 0, 3, 0, 0, 8, 0]], "clues": 35, "id": -2998325238861906031}, {"puzzle": [[0, 0, 3, 4, 8, 1, 9, 0, 0], [1, 0, 0, 0, 0, 2, 8, 0, 0], [0, 0, 0, 3, 9, 0, 6, 1, 0], [3, 6, 1, 8, 0, 7, 0, 0, 0], [5, 0, 0, 1, 0, 0, 0, 7, 0], [0, 0, 7, 0, 0, 0, 1, 0, 0], [0, 7, 0, 9, 5, 0, 2, 0, 0], [0, 0, 0, 0, 1, 0, 7, 0, 5], [2, 0, 0, 7, 0, 4, 3, 8, 9]], "clues": 35, "id": 5551274746869175706}, {"puzzle": [[0, 0, 4, 8, 5, 0, 0, 0, 0], [0, 0, 0, 2, 0, 0, 4, 0, 6], [1, 3, 0, 9, 6, 4, 2, 0, 8], [0, 0, 8, 0, 0, 0, 5, 0, 0], [0, 1, 0, 4, 9, 0, 0, 8, 0], [0, 0, 0, 0, 0, 0, 1, 6, 9], [6, 7, 0, 3, 0, 0, 0, 1, 0], [0, 0, 5, 0, 2, 6, 0, 7, 3], [3, 0, 1, 5, 0, 8, 0, 0, 0]], "clues": 35, "id": -611911145474831430}, {"puzzle": [[6, 0, 1, 2, 0, 0, 0, 0, 5], [0, 0, 0, 1, 0, 7, 0, 6, 8], [0, 0, 0, 0, 8, 5, 0, 0, 0], [0, 0, 0, 4, 2, 6, 0, 0, 3], [2, 9, 0, 5, 3, 0, 8, 0, 0], [0, 3, 0, 0, 7, 9, 6, 0, 0], [0, 0, 2, 9, 0, 0, 0, 3, 0], [9, 7, 0, 3, 1, 0, 5, 0, 0], [0, 1, 0, 0, 0, 2, 9, 8, 0]], "clues": 35, "id": 3089762909516907131}, {"puzzle": [[4, 3, 0, 0, 1, 0, 5, 8, 7], [9, 0, 0, 7, 0, 8, 0, 0, 4], [0, 0, 0, 0, 5, 3, 0, 0, 0], [7, 1, 0, 6, 3, 0, 4, 0, 9], [3, 0, 5, 8, 0, 0, 2, 0, 0], [0, 0, 0, 0, 7, 0, 0, 6, 8], [0, 9, 0, 0, 8, 0, 0, 0, 3], [0, 2, 0, 0, 0, 0, 8, 4, 6], [1, 0, 0, 0, 0, 0, 0, 2, 5]], "clues": 35, "id": -2165460823807024299}, {"puzzle": [[5, 0, 0, 0, 0, 4, 1, 0, 0], [1, 8, 6, 3, 0, 2, 0, 4, 0], [9, 0, 4, 6, 0, 5, 0, 0, 8], [0, 6, 0, 4, 3, 0, 0, 9, 0], [3, 0, 0, 2, 0, 0, 0, 0, 0], [0, 0, 5, 8, 6, 9, 0, 7, 0], [0, 0, 3, 1, 0, 0, 9, 0, 0], [0, 9, 0, 5, 0, 3, 2, 0, 4], [0, 0, 0, 9, 0, 0, 8, 0, 0]], "clues": 35, "id": 387951431653451725}, {"puzzle": [[0, 3, 4, 0, 0, 6, 7, 0, 0], [0, 0, 8, 0, 0, 0, 4, 0, 0], [6, 0, 0, 0, 0, 1, 2, 0, 8], [7, 0, 1, 5, 0, 0, 8, 2, 0], [0, 8, 0, 7, 0, 0, 1, 0, 0], [0, 6, 3, 2, 0, 8, 9, 0, 0], [0, 0, 9, 0, 0, 7, 6, 8, 2], [0, 0, 0, 9, 2, 0, 0, 0, 0], [0, 0, 7, 0, 8, 3, 5, 0, 9]], "clues": 35, "id": -2376203700489421537}, {"puzzle": [[0, 1, 0, 0, 4, 0, 0, 0, 0], [0, 4, 0, 0, 1, 0, 0, 6, 0], [6, 0, 2, 3, 0, 5, 0, 0, 0], [4, 5, 0, 2, 3, 6, 0, 0, 1], [0, 3, 0, 5, 0, 9, 2, 0, 6], [9, 2, 0, 0, 0, 0, 0, 0, 3], [3, 6, 0, 8, 0, 4, 0, 7, 0], [2, 9, 4, 0, 0, 0, 0, 0, 8], [8, 0, 0, 0, 6, 0, 0, 0, 4]], "clues": 35, "id": -3914595753431195167}, {"puzzle": [[5, 0, 9, 0, 0, 8, 0, 0, 2], [0, 0, 0, 0, 9, 5, 7, 0, 0], [0, 6, 0, 0, 7, 3, 9, 0, 0], [0, 0, 0, 9, 0, 6, 0, 0, 0], [0, 9, 8, 0, 5, 2, 4, 0, 0], [7, 5, 0, 0, 0, 0, 6, 0, 0], [4, 0, 0, 0, 3, 7, 1, 0, 9], [0, 0, 7, 6, 1, 0, 5, 0, 3], [1, 0, 6, 0, 2, 9, 0, 0, 0]], "clues": 35, "id": -6325786395216000137}, {"puzzle": [[2, 0, 6, 4, 8, 0, 0, 7, 0], [0, 0, 8, 0, 0, 0, 0, 0, 0], [9, 0, 1, 3, 0, 0, 8, 0, 0], [4, 0, 7, 2, 9, 0, 1, 8, 0], [1, 5, 0, 6, 4, 0, 0, 0, 7], [8, 0, 3, 5, 0, 7, 0, 0, 2], [3, 1, 5, 7, 0, 9, 0, 0, 0], [6, 0, 9, 0, 0, 0, 0, 0, 1], [0, 0, 4, 0, 0, 0, 0, 0, 0]], "clues": 35, "id": 7774623981293904006}, {"puzzle": [[1, 0, 0, 5, 4, 0, 7, 8, 0], [0, 0, 0, 0, 0, 0, 0, 0, 1], [0, 4, 8, 0, 1, 6, 0, 0, 9], [0, 0, 0, 0, 0, 0, 8, 0, 3], [0, 0, 0, 6, 7, 0, 1, 2, 0], [0, 2, 0, 4, 8, 0, 0, 0, 5], [8, 0, 0, 2, 0, 4, 0, 0, 0], [0, 7, 2, 0, 3, 1, 0, 5, 0], [0, 5, 4, 0, 6, 7, 0, 1, 2]], "clues": 35, "id": 6931377912677584553}, {"puzzle": [[0, 0, 3, 0, 0, 0, 0, 9, 0], [9, 0, 2, 0, 6, 8, 0, 0, 0], [0, 0, 4, 9, 2, 1, 6, 5, 0], [0, 0, 0, 0, 0, 5, 0, 0, 0], [6, 0, 0, 8, 7, 0, 1, 4, 5], [0, 0, 5, 6, 0, 9, 8, 7, 0], [0, 4, 0, 0, 0, 7, 0, 2, 0], [5, 0, 6, 0, 0, 0, 0, 0, 1], [7, 2, 0, 5, 0, 0, 9, 3, 0]], "clues": 35, "id": -3225908880725173526}, {"puzzle": [[0, 0, 0, 0, 0, 8, 0, 0, 0], [0, 0, 7, 0, 6, 0, 2, 0, 0], [5, 4, 8, 0, 0, 0, 7, 9, 6], [0, 0, 0, 9, 3, 0, 0, 0, 8], [0, 0, 3, 0, 0, 0, 0, 2, 9], [1, 6, 9, 0, 0, 0, 5, 0, 0], [6, 9, 0, 0, 2, 0, 8, 1, 4], [0, 0, 0, 1, 0, 0, 6, 7, 0], [3, 7, 0, 4, 0, 6, 0, 5, 2]], "clues": 35, "id": -2202177880348155994}, {"puzzle": [[7, 0, 3, 0, 0, 0, 0, 0, 0], [4, 0, 9, 7, 6, 0, 0, 2, 3], [2, 6, 8, 5, 0, 0, 0, 0, 9], [6, 0, 0, 0, 1, 4, 3, 5, 0], [0, 8, 4, 3, 0, 7, 0, 0, 0], [5, 0, 0, 0, 0, 6, 0, 1, 0], [0, 0, 6, 0, 7, 3, 0, 0, 0], [0, 7, 0, 0, 0, 0, 0, 8, 6], [0, 4, 0, 0, 8, 2, 0, 0, 1]], "clues": 35, "id": 1277994466147921514}, {"puzzle": [[0, 5, 8, 0, 0, 3, 0, 0, 6], [0, 0, 3, 0, 2, 0, 7, 5, 0], [4, 0, 2, 0, 6, 0, 1, 3, 0], [0, 0, 0, 8, 0, 0, 0, 0, 1], [6, 0, 0, 2, 0, 5, 8, 0, 0], [0, 0, 7, 0, 1, 6, 0, 4, 0], [0, 9, 0, 0, 5, 0, 6, 1, 0], [0, 3, 6, 7, 0, 0, 2, 0, 4], [0, 0, 0, 0, 9, 4, 3, 0, 0]], "clues": 35, "id": -7732834119061977112}, {"puzzle": [[0, 0, 0, 0, 0, 8, 0, 4, 0], [7, 4, 6, 2, 3, 0, 0, 0, 1], [0, 0, 3, 6, 4, 0, 0, 0, 2], [0, 3, 2, 0, 7, 0, 0, 0, 0], [0, 8, 9, 0, 6, 0, 2, 3, 7], [5, 0, 7, 0, 9, 0, 0, 0, 4], [6, 0, 0, 1, 5, 3, 0, 0, 9], [0, 0, 0, 4, 8, 0, 0, 5, 0], [0, 0, 0, 0, 0, 0, 7, 0, 8]], "clues": 35, "id": -8116768174774283212}, {"puzzle": [[6, 0, 3, 0, 8, 0, 0, 0, 1], [9, 0, 4, 3, 0, 6, 0, 0, 8], [7, 8, 0, 0, 0, 0, 3, 9, 0], [0, 0, 0, 0, 3, 2, 0, 0, 9], [8, 4, 0, 0, 0, 9, 0, 0, 7], [0, 6, 0, 0, 0, 1, 4, 0, 0], [4, 0, 5, 0, 2, 0, 0, 0, 0], [0, 9, 0, 6, 0, 0, 5, 0, 2], [2, 3, 0, 0, 9, 0, 8, 1, 0]], "clues": 35, "id": 3115293493265870184}, {"puzzle": [[0, 0, 0, 0, 7, 9, 0, 8, 0], [0, 0, 0, 0, 0, 0, 0, 0, 7], [7, 0, 8, 6, 5, 1, 0, 0, 0], [0, 0, 3, 0, 0, 5, 2, 7, 0], [5, 1, 7, 9, 6, 0, 8, 0, 3], [0, 0, 0, 4, 0, 0, 1, 6, 5], [0, 9, 0, 1, 0, 0, 7, 5, 0], [0, 7, 6, 5, 0, 4, 0, 0, 2], [1, 0, 0, 0, 0, 0, 0, 9, 0]], "clues": 35, "id": -4602056402870091552}, {"puzzle": [[5, 4, 7, 0, 0, 0, 6, 0, 8], [0, 0, 0, 0, 7, 8, 0, 0, 0], [2, 0, 8, 0, 6, 9, 0, 0, 0], [8, 5, 0, 0, 3, 4, 7, 2, 6], [0, 0, 0, 0, 8, 6, 0, 5, 0], [0, 0, 0, 0, 0, 0, 3, 0, 0], [9, 7, 5, 0, 0, 0, 8, 4, 3], [0, 0, 2, 0, 0, 7, 0, 0, 9], [0, 0, 0, 9, 0, 0, 2, 1, 7]], "clues": 35, "id": 7476353522162871814}, {"puzzle": [[0, 0, 0, 1, 6, 0, 3, 0, 0], [3, 7, 0, 0, 9, 0, 4, 0, 0], [4, 0, 0, 8, 0, 3, 2, 5, 6], [7, 3, 0, 0, 0, 0, 6, 0, 5], [0, 6, 0, 0, 1, 0, 0, 3, 0], [0, 5, 0, 0, 3, 0, 8, 1, 0], [5, 9, 0, 0, 0, 7, 0, 0, 8], [0, 0, 7, 9, 0, 8, 5, 0, 3], [0, 0, 0, 3, 0, 1, 0, 0, 0]], "clues": 35, "id": 318261896453034724}, {"puzzle": [[4, 0, 2, 6, 0, 0, 0, 0, 1], [0, 3, 0, 0, 2, 9, 0, 7, 0], [0, 0, 6, 0, 0, 0, 0, 2, 4], [2, 0, 7, 0, 0, 0, 0, 9, 8], [0, 0, 3, 0, 8, 2, 0, 4, 0], [8, 1, 0, 5, 0, 3, 2, 0, 7], [0, 0, 0, 0, 3, 0, 0, 0, 9], [0, 2, 8, 0, 4, 1, 0, 5, 0], [0, 0, 9, 0, 0, 7, 0, 1, 0]], "clues": 35, "id": 5903107011669958920}, {"puzzle": [[3, 0, 5, 0, 0, 0, 1, 0, 0], [0, 0, 0, 0, 1, 0, 9, 5, 0], [0, 7, 0, 0, 0, 5, 4, 6, 0], [0, 8, 0, 0, 4, 0, 7, 9, 0], [0, 0, 0, 0, 7, 0, 0, 2, 0], [0, 5, 2, 8, 0, 0, 3, 0, 1], [0, 2, 4, 7, 3, 0, 6, 0, 9], [0, 9, 0, 4, 0, 8, 5, 0, 0], [0, 0, 7, 9, 0, 6, 0, 1, 0]], "clues": 35, "id": 4296231860837281456}, {"puzzle": [[0, 4, 5, 6, 1, 0, 0, 2, 0], [0, 7, 0, 8, 4, 5, 0, 6, 0], [1, 0, 0, 3, 9, 0, 0, 5, 0], [8, 0, 0, 0, 0, 0, 6, 3, 9], [5, 1, 0, 0, 6, 0, 7, 0, 0], [7, 0, 0, 0, 0, 0, 1, 0, 5], [0, 5, 0, 0, 3, 0, 2, 0, 6], [0, 3, 0, 0, 0, 6, 0, 1, 0], [0, 0, 0, 0, 0, 0, 5, 9, 3]], "clues": 35, "id": -4577685178918047139}, {"puzzle": [[0, 0, 0, 6, 0, 0, 0, 0, 9], [7, 5, 0, 0, 4, 0, 0, 8, 0], [0, 8, 0, 0, 0, 0, 4, 0, 7], [0, 1, 0, 3, 8, 0, 0, 0, 0], [0, 7, 9, 0, 1, 2, 0, 3, 0], [0, 0, 3, 0, 0, 7, 8, 0, 0], [4, 6, 0, 7, 5, 3, 9, 0, 0], [5, 9, 7, 0, 2, 0, 3, 0, 6], [3, 2, 0, 0, 0, 0, 5, 0, 0]], "clues": 35, "id": -2469109582505236736}, {"puzzle": [[0, 0, 0, 4, 0, 0, 9, 2, 1], [0, 0, 9, 0, 0, 3, 0, 0, 4], [0, 0, 4, 0, 9, 1, 3, 7, 0], [5, 0, 2, 7, 4, 8, 0, 0, 0], [0, 4, 1, 5, 2, 0, 0, 0, 0], [0, 0, 0, 3, 0, 9, 0, 4, 5], [1, 9, 3, 0, 0, 0, 0, 5, 0], [0, 0, 0, 0, 0, 0, 0, 6, 7], [7, 0, 0, 1, 0, 4, 0, 0, 3]], "clues": 35, "id": -2041652516576997871}, {"puzzle": [[4, 9, 0, 6, 1, 0, 7, 0, 8], [0, 1, 0, 0, 3, 5, 0, 9, 0], [6, 0, 0, 9, 0, 7, 0, 0, 0], [0, 6, 0, 0, 0, 0, 0, 8, 0], [0, 0, 0, 0, 5, 0, 0, 0, 0], [0, 7, 4, 0, 6, 9, 0, 3, 1], [2, 4, 0, 0, 0, 0, 8, 0, 0], [7, 0, 0, 1, 4, 8, 5, 2, 0], [9, 0, 5, 0, 0, 0, 0, 4, 3]], "clues": 35, "id": 4783388603611615438}, {"puzzle": [[0, 3, 0, 0, 0, 0, 5, 0, 0], [1, 0, 9, 0, 7, 4, 8, 0, 0], [0, 0, 0, 5, 0, 0, 0, 0, 1], [9, 6, 1, 0, 0, 0, 0, 4, 7], [5, 0, 0, 7, 0, 1, 0, 0, 6], [8, 7, 0, 0, 6, 2, 3, 1, 0], [0, 0, 0, 3, 0, 9, 0, 5, 2], [0, 9, 0, 0, 0, 0, 0, 0, 8], [2, 4, 0, 1, 0, 0, 6, 3, 0]], "clues": 35, "id": -3264854645278361496}, {"puzzle": [[5, 3, 7, 0, 1, 0, 6, 0, 4], [0, 9, 4, 3, 8, 0, 0, 5, 0], [1, 2, 0, 0, 0, 5, 0, 0, 3], [0, 0, 0, 0, 2, 0, 0, 0, 7], [0, 0, 0, 0, 0, 3, 4, 0, 8], [0, 4, 5, 0, 0, 0, 2, 0, 0], [0, 5, 2, 0, 3, 8, 9, 7, 6], [0, 0, 0, 0, 5, 0, 0, 4, 0], [9, 0, 0, 0, 0, 0, 8, 2, 0]], "clues": 35, "id": -1518210035176436007}, {"puzzle": [[0, 0, 0, 0, 0, 5, 0, 3, 4], [3, 8, 9, 0, 2, 0, 7, 0, 0], [0, 4, 0, 8, 3, 6, 1, 0, 9], [0, 5, 0, 9, 0, 2, 6, 1, 8], [0, 0, 0, 5, 0, 0, 3, 0, 2], [0, 6, 0, 0, 8, 0, 0, 0, 0], [9, 0, 4, 6, 0, 0, 0, 8, 1], [8, 0, 0, 2, 0, 0, 0, 5, 0], [0, 2, 0, 0, 4, 0, 0, 0, 0]], "clues": 35, "id": 8090518022078886450}, {"puzzle": [[0, 0, 0, 0, 4, 0, 5, 0, 0], [5, 0, 9, 0, 0, 6, 2, 1, 4], [0, 0, 6, 0, 2, 5, 3, 0, 7], [2, 0, 1, 0, 0, 0, 0, 0, 0], [0, 0, 0, 0, 5, 0, 9, 4, 1], [0, 0, 4, 0, 3, 8, 0, 0, 0], [1, 0, 5, 0, 0, 0, 0, 3, 8], [0, 0, 8, 7, 1, 9, 0, 0, 5], [0, 4, 2, 0, 0, 0, 0, 9, 6]], "clues": 35, "id": -3531614082911206536}, {"puzzle": [[0, 0, 0, 0, 0, 4, 0, 7, 0], [0, 0, 7, 0, 0, 1, 0, 0, 0], [0, 0, 4, 7, 6, 0, 0, 2, 0], [0, 9, 0, 0, 0, 0, 0, 1, 2], [6, 7, 8, 1, 2, 5, 0, 9, 4], [0, 0, 3, 9, 0, 0, 0, 0, 7], [0, 0, 6, 0, 0, 0, 0, 0, 0], [7, 8, 2, 6, 9, 3, 0, 0, 0], [3, 4, 1, 8, 0, 2, 7, 0, 0]], "clues": 35, "id": 8832296125680577995}, {"puzzle": [[0, 5, 0, 6, 0, 8, 7, 0, 0], [7, 0, 0, 0, 0, 0, 0, 0, 6], [0, 0, 0, 0, 9, 7, 0, 3, 0], [0, 1, 4, 0, 0, 6, 9, 0, 7], [9, 7, 0, 0, 1, 0, 0, 4, 8], [6, 2, 0, 7, 4, 9, 1, 5, 3], [0, 0, 0, 0, 0, 0, 4, 0, 0], [0, 0, 6, 0, 0, 0, 8, 0, 5], [0, 0, 5, 8, 6, 0, 0, 0, 2]], "clues": 35, "id": 3575929185153279235}, {"puzzle": [[7, 0, 2, 0, 4, 0, 0, 5, 0], [3, 0, 5, 0, 0, 0, 7, 0, 0], [0, 0, 0, 0, 7, 9, 0, 0, 0], [0, 0, 4, 0, 0, 3, 9, 0, 1], [9, 6, 0, 1, 2, 0, 5, 0, 3], [0, 0, 3, 0, 0, 0, 4, 8, 0], [0, 2, 9, 4, 0, 5, 3, 0, 0], [4, 0, 6, 0, 3, 2, 0, 0, 5], [5, 0, 0, 9, 0, 0, 6, 0, 0]], "clues": 35, "id": -1454012572155178534}, {"puzzle": [[0, 3, 5, 0, 1, 0, 2, 4, 6], [0, 0, 0, 3, 0, 2, 9, 0, 5], [6, 0, 0, 5, 0, 9, 0, 3, 0], [7, 8, 0, 0, 0, 0, 0, 1, 0], [0, 0, 0, 0, 3, 1, 0, 5, 0], [0, 0, 3, 6, 0, 0, 0, 8, 2], [0, 6, 0, 0, 0, 0, 8, 0, 4], [0, 5, 4, 0, 0, 0, 7, 0, 0], [3, 9, 8, 0, 7, 4, 0, 0, 0]], "clues": 35, "id": 5557349982313553878}, {"puzzle": [[0, 0, 4, 5, 9, 0, 3, 2, 1], [0, 0, 3, 1, 0, 4, 8, 7, 6], [0, 0, 0, 0, 0, 0, 0, 0, 4], [0, 2, 0, 0, 7, 6, 0, 3, 0], [0, 0, 0, 0, 8, 0, 0, 0, 5], [3, 8, 0, 0, 0, 1, 7, 0, 9], [0, 6, 0, 0, 0, 2, 0, 8, 7], [0, 0, 0, 0, 6, 0, 0, 0, 3], [1, 3, 0, 8, 0, 9, 6, 0, 0]], "clues": 35, "id": -1371061787111733059}, {"puzzle": [[0, 0, 7, 6, 0, 2, 1, 0, 5], [5, 0, 0, 7, 3, 0, 0, 0, 9], [0, 0, 3, 0, 0, 0, 0, 0, 0], [0, 1, 0, 2, 0, 7, 9, 5, 4], [2, 9, 8, 0, 0, 0, 7, 0, 3], [7, 0, 0, 0, 0, 3, 0, 1, 0], [0, 0, 0, 0, 0, 0, 5, 8, 6], [0, 0, 9, 0, 5, 1, 0, 0, 2], [8, 5, 2, 0, 0, 0, 3, 0, 0]], "clues": 35, "id": -2072856013419836448}, {"puzzle": [[2, 5, 3, 4, 9, 0, 7, 1, 8], [1, 4, 0, 5, 2, 0, 6, 0, 0], [0, 9, 0, 0, 0, 8, 5, 4, 0], [0, 8, 0, 0, 7, 0, 0, 9, 0], [0, 0, 9, 0, 0, 1, 0, 0, 5], [4, 6, 0, 8, 0, 0, 0, 0, 7], [0, 3, 0, 9, 0, 5, 2, 0, 0], [0, 0, 0, 0, 0, 0, 0, 5, 0], [9, 2, 0, 0, 0, 0, 0, 0, 3]], "clues": 35, "id": -4482666366718396895}, {"puzzle": [[0, 5, 9, 3, 0, 7, 2, 6, 1], [4, 0, 0, 0, 6, 0, 8, 5, 0], [0, 6, 0, 5, 8, 9, 0, 4, 0], [3, 9, 0, 0, 0, 0, 4, 0, 2], [0, 0, 0, 0, 3, 0, 0, 9, 5], [6, 1, 0, 4, 9, 0, 0, 8, 0], [0, 2, 0, 0, 0, 3, 9, 7, 4], [9, 8, 0, 0, 0, 0, 0, 0, 0], [0, 0, 0, 0, 0, 0, 0, 0, 0]], "clues": 35, "id": -8140658652808193283}, {"puzzle": [[0, 0, 2, 0, 0, 1, 5, 3, 0], [5, 7, 0, 0, 0, 0, 0, 0, 0], [0, 3, 1, 0, 5, 0, 4, 0, 6], [0, 0, 0, 3, 4, 6, 9, 0, 0], [0, 2, 0, 5, 1, 9, 0, 0, 0], [0, 0, 4, 0, 8, 0, 1, 0, 0], [2, 0, 9, 0, 0, 8, 0, 0, 1], [0, 4, 0, 1, 9, 0, 6, 2, 7], [1, 0, 0, 0, 2, 0, 0, 0, 5]], "clues": 35, "id": 755430926744556193}],
	"medium": [{"puzzle": [[0, 0, 0, 0, 0, 0, 0, 0, 7], [1, 6, 0, 0, 0, 0, 4, 3, 0], [3, 0, 7, 0, 4, 0, 0, 0, 6], [0, 4, 6, 0, 0, 3, 5, 0, 0], [0, 1, 0, 0, 0, 0, 6, 7, 0], [2, 0, 5, 0, 0, 6, 9, 0, 0], [6, 0, 3, 0, 1, 0, 0, 0, 4], [0, 0, 4, 0, 0, 7, 0, 0, 1], [0, 0, 0, 4, 0, 8, 7, 0, 0]], "clues": 30, "id": -6769906843017411674}, {"puzzle": [[0, 0, 4, 0, 2, 1, 0, 9, 0], [0, 5, 0, 0, 0, 0, 0, 2, 4], [0, 7, 0, 0, 0, 4, 0, 6, 0], [0, 0, 0, 0, 0, 0, 4, 0, 0], [7, 0, 8, 0, 1, 0, 6, 0, 9], [6, 0, 0, 0, 0, 0, 2, 0, 0], [0, 9, 3, 0, 0, 8, 0, 7, 6], [0, 0, 0, 1, 7, 0, 0, 0, 2], [0, 0, 0, 0, 5, 6, 8, 0, 3]], "clues": 30, "id": 2038636185487312952}, {"puzzle": [[0, 0, 8, 0, 0, 0, 2, 3, 0], [0, 0, 0, 0, 6, 0, 8, 0, 7], [9, 2, 0, 0, 3, 0, 0, 0, 6], [0, 0, 5, 7, 0, 8, 6, 0, 0], [3, 0, 2, 1, 0, 6, 0, 0, 4], [0, 7, 0, 0, 0, 0, 0, 0, 0], [0, 0, 0, 0, 7, 3, 4, 0, 0], [0, 8, 0, 0, 1, 0, 3, 7, 9], [0, 0, 0, 4, 0, 9, 0, 0, 0]], "clues": 30, "id": 654076644182324116}, {"puzzle": [[0, 0, 0, 0, 0, 2, 3, 0, 7], [0, 5, 0, 8, 7, 0, 0, 1, 0], [0, 0, 2, 0, 0, 6, 0, 8, 0], [0, 9, 3, 0, 0, 0, 4, 0, 6], [0, 2, 0, 0, 3, 0, 0, 9, 0], [5, 0, 8, 9, 0, 0, 7, 0, 0], [4, 0, 0, 0, 0, 3, 0, 0, 0], [0, 3, 0, 0, 9, 8, 0, 4, 0], [0, 0, 0, 4, 0, 0, 6, 0, 2]], "clues": 30, "id": 594568590545014555}, {"puzzle": [[0, 0, 0, 0, 0, 2, 0, 0, 0], [4, 0, 0, 0, 0, 0, 2, 0, 5], [0, 6, 1, 0, 7, 0, 0, 4, 0], [0, 0, 0, 0, 5, 8, 0, 7, 3], [0, 0, 8, 0, 4, 3, 5, 2, 0], [5, 3, 0, 7, 0, 0, 4, 0, 0], [0, 7, 0, 0, 0, 0, 0, 5, 0], [8, 0, 3, 0, 0, 4, 0, 0, 2], [0, 0, 5, 8, 0, 0, 0, 0, 4]], "clues": 30, "id": 98472367842935053}, {"puzzle": [[0, 2, 7, 0, 1, 0, 5, 0, 0], [0, 0, 3, 0, 0, 0, 8, 1, 0], [4, 0, 0, 0, 0, 0, 0, 0, 6], [0, 5, 4, 0, 0, 0, 0, 3, 7], [1, 0, 0, 0, 0, 0, 4, 0, 5], [0, 0, 0, 3, 0, 4, 0, 0, 0], [0, 0, 0, 5, 0, 7, 0, 6, 0], [0, 7, 6, 9, 0, 1, 3, 0, 0], [5, 4, 0, 0, 6, 0, 0, 0, 1]], "clues": 30, "id": -488505775393971331}, {"puzzle": [[0, 3, 0, 0, 0, 0, 4, 0, 0], [0, 4, 5, 0, 0, 0, 0, 7, 0], [8, 0, 0, 2, 3, 0, 0, 0, 5], [7, 0, 3, 5, 0, 0, 0, 0, 6], [0, 6, 4, 0, 0, 0, 3, 0, 0], [0, 0, 0, 0, 6, 3, 5, 0, 0], [0, 0, 0, 0, 5, 7, 9, 0, 0], [0, 1, 8, 3, 0, 6, 0, 5, 0], [0, 0, 0, 0, 9, 0, 0, 3, 2]], "clues": 30, "id": 4952624511070701501}, {"puzzle": [[0, 7, 0, 0, 0, 0, 1, 6, 0], [0, 8, 3, 0, 7, 0, 0, 2, 0], [0, 0, 0, 2, 8, 0, 0, 4, 0], [8, 0, 0, 1, 0, 0, 0, 0, 6], [0, 0, 0, 9, 6, 5, 0, 0, 0], [5, 9, 0, 0, 0, 0, 0, 3, 1], [0, 0, 0, 7, 4, 0, 6, 0, 0], [9, 0, 0, 0, 0, 2, 7, 0, 0], [0, 4, 0, 0, 0, 0, 2, 1, 3]], "clues": 30, "id": 5186593831779011192}, {"puzzle": [[0, 0, 5, 0, 0, 4, 3, 0, 0], [0, 9, 6, 0, 1, 0, 0, 0, 0], [2, 0, 0, 0, 0, 0, 0, 8, 7], [4, 2, 0, 0, 0, 8, 0, 9, 0], [0, 0, 0, 4, 0, 0, 8, 0, 0], [0, 6, 0, 1, 0, 0, 0, 4, 5], [6, 0, 0, 0, 0, 5, 0, 0, 4], [3, 0, 0, 0, 6, 0, 5, 7, 0], [0, 0, 9, 0, 4, 3, 2, 0, 0]], "clues": 30, "id": -5072223015090495338}, {"puzzle": [[0, 0, 3, 0, 0, 0, 7, 0, 0], [0, 4, 0, 0, 0, 7, 0, 3, 8], [0, 0, 0, 0, 3, 4, 0, 6, 0], [4, 0, 7, 5, 0, 0, 0, 0, 0], [8, 0, 0, 0, 0, 0, 0, 0, 1], [0, 5, 1, 0, 0, 9, 0, 0, 0], [6, 0, 0, 7, 2, 0, 1, 0, 5], [2, 1, 0, 0, 6, 0, 0, 9, 0], [0, 0, 5, 0, 4, 0, 3, 0, 6]], "clues": 30, "id": 6332356199135325966}, {"puzzle": [[0, 8, 0, 0, 2, 7, 0, 6, 0], [0, 0, 0, 8, 0, 4, 5, 0, 1], [7, 1, 0, 0, 0, 0, 0, 8, 0], [8, 0, 0, 0, 0, 0, 3, 0, 0], [0, 0, 0, 4, 0, 8, 0, 0, 2], [0, 0, 2, 0, 5, 0, 0, 0, 7], [0, 4, 0, 7, 0, 0, 0, 3, 0], [3, 0, 0, 5, 6, 2, 0, 0, 0], [1, 0, 0, 0, 4, 0, 0, 2, 6]], "clues": 30, "id": -1792222721705443729}, {"puzzle": [[0, 0, 9, 7, 0, 3, 0, 0, 6], [4, 0, 2, 0, 0, 0, 5, 0, 0], [0, 8, 0, 4, 5, 0, 0, 0, 2], [0, 1, 8, 0, 9, 0, 0, 3, 0], [5, 0, 0, 0, 0, 0, 0, 0, 4], [0, 4, 0, 0, 6, 7, 0, 5, 0], [0, 0, 0, 0, 7, 6, 2, 1, 0], [7, 0, 0, 0, 0, 0, 0, 0, 0], [8, 0, 0, 9, 0, 5, 0, 6, 0]], "clues": 30, "id": 1036639612744581964}, {"puzzle": [[0, 0, 0, 2, 0, 0, 0, 0, 0], [2, 0, 5, 0, 6, 0, 0, 7, 0], [0, 0, 9, 0, 0, 0, 1, 8, 0], [1, 0, 0, 8, 0, 0, 7, 0, 4], [5, 3, 0, 1, 0, 0, 0, 0, 8], [8, 0, 0, 3, 0, 0, 0, 0, 9], [0, 2, 8, 7, 0, 0, 6, 0, 0], [0, 0, 0, 0, 2, 4, 8, 0, 1], [0, 4, 1, 0, 0, 9, 0, 0, 0]], "clues": 30, "id": -8263313341624468505}, {"puzzle": [[0, 0, 0, 1, 5, 8, 0, 0, 0], [0, 0, 0, 0, 4, 0, 3, 0, 1], [0, 1, 0, 0, 0, 0, 6, 5, 0], [0, 0, 0, 0, 0, 3, 5, 0, 0], [6, 0, 0, 4, 0, 2, 0, 0, 3], [7, 0, 3, 5, 0, 0, 0, 0, 8], [0, 6, 0, 0, 0, 0, 0, 4, 0], [0, 5, 0, 6, 2, 0, 9, 0, 0], [4, 3, 0, 0, 1, 0, 0, 6, 2]], "clues": 30, "id": -5624055803168688082}, {"puzzle": [[0, 0, 9, 0, 0, 0, 5, 0, 8], [7, 0, 5, 0, 0, 8, 0, 6, 0], [0, 0, 0, 0, 4, 5, 0, 0, 9], [0, 6, 0, 8, 0, 0, 4, 9, 0], [0, 8, 0, 9, 7, 0, 0, 0, 0], [9, 0, 0, 0, 0, 3, 0, 0, 0], [4, 0, 0, 5, 8, 0, 0, 2, 0], [6, 3, 0, 0, 0, 0, 7, 0, 0], [0, 0, 0, 7, 3, 2, 0, 4, 0]], "clues": 30, "id": 5817083122284374466}, {"puzzle": [[0, 0, 2, 8, 0, 3, 0, 1, 0], [1, 0, 0, 0, 0, 0, 0, 2, 5], [0, 0, 6, 0, 0, 0, 3, 0, 0], [0, 4, 0, 0, 3, 0, 0, 0, 0], [0, 0, 9, 0, 1, 0, 6, 0, 0], [0, 0, 0, 4, 8, 6, 0, 9, 0], [8, 0, 4, 0, 0, 0, 7, 0, 1], [7, 0, 0, 0, 2, 0, 8, 0, 9], [0, 9, 0, 3, 0, 8, 2, 0, 0]], "clues": 30, "id": 2095414671654606677}, {"puzzle": [[0, 9, 0, 6, 4, 0, 0, 0, 0], [7, 0, 6, 0, 9, 0, 5, 0, 0], [0, 0, 0, 0, 0, 7, 6, 0, 0], [0, 3, 0, 1, 0, 0, 0, 5, 0], [5, 0, 0, 3, 0, 8, 4, 0, 0], [0, 1, 9, 0, 0, 4, 0, 3, 0], [9, 0, 0, 0, 0, 6, 0, 0, 0], [0, 0, 3, 0, 5, 0, 7, 0, 8], [6, 0, 0, 0, 1, 0, 0, 2, 4]], "clues": 30, "id": 6823093080972216546}, {"puzzle": [[0, 7, 0, 0, 0, 0, 0, 8, 0], [0, 2, 3, 0, 0, 6, 0, 9, 0], [0, 0, 0, 0, 3, 7, 0, 0, 6], [9, 0, 7, 0, 0, 0, 8, 0, 4], [0, 6, 0, 0, 9, 0, 0, 5, 0], [5, 0, 4, 0, 0, 0, 9, 0, 2], [0, 0, 0, 0, 4, 0, 0, 7, 8], [0, 0, 6, 0, 1, 3, 0, 0, 0], [0, 8, 0, 7, 0, 9, 0, 1, 0]], "clues": 30, "id": -8587973115326976623}, {"puzzle": [[0, 0, 0, 0, 1, 0, 6, 8, 0], [9, 3, 4, 0, 0, 0, 0, 7, 0], [8, 0, 6, 0, 7, 0, 0, 0, 5], [0, 0, 8, 4, 0, 0, 0, 0, 7], [0, 6, 0, 0, 0, 8, 0, 9, 0], [0, 0, 0, 9, 0, 0, 0, 0, 6], [3, 0, 5, 0, 9, 0, 0, 0, 8], [0, 8, 0, 0, 0, 3, 0, 5, 0], [0, 0, 0, 5, 0, 2, 0, 6, 3]], "clues": 30, "id": -7648908501160650114}, {"puzzle": [[0, 0, 3, 0, 0, 2, 0, 6, 0], [1, 0, 0, 0, 0, 0, 0, 0, 7], [0, 0, 7, 1, 0, 9, 3, 0, 0], [0, 3, 0, 7, 9, 0, 0, 4, 0], [0, 0, 5, 0, 2, 0, 1, 0, 0], [0, 7, 0, 0, 1, 4, 0, 3, 0], [0, 0, 0, 4, 0, 7, 0, 0, 6], [5, 1, 0, 0, 0, 0, 0, 0, 4], [0, 0, 0, 9, 6, 0, 5, 8, 0]], "clues": 30, "id": -5265514463139413832}, {"puzzle": [[0, 0, 2, 7, 0, 0, 3, 0, 0], [0, 9, 0, 8, 0, 0, 0, 1, 0], [0, 1, 0, 3, 0, 0, 9, 8, 0], [1, 0, 9, 0, 0, 0, 0, 0, 0], [0, 0, 0, 5, 3, 9, 0, 0, 1], [5, 3, 0, 0, 0, 0, 4, 7, 0], [0, 0, 0, 6, 8, 0, 1, 0, 0], [0, 5, 1, 0, 0, 7, 0, 6, 0], [0, 0, 3, 0, 0, 5, 7, 0, 0]], "clues": 30, "id": 1932875207317447973}, {"puzzle": [[0, 0, 0, 6, 0, 0, 9, 2, 5], [9, 3, 0, 0, 5, 0, 0, 0, 0], [0, 0, 6, 0, 9, 8, 1, 0, 0], [0, 0, 2, 7, 0, 0, 6, 9, 0], [0, 7, 0, 0, 0, 0, 0, 1, 0], [3, 0, 0, 0, 0, 0, 0, 0, 0], [0, 0, 3, 0, 4, 9, 7, 0, 1], [7, 4, 0, 0, 6, 0, 0, 0, 0], [0, 1, 0, 0, 0, 5, 3, 0, 6]], "clues": 30, "id": 2031122126412706668}, {"puzzle": [[0, 0, 0, 6, 1, 2, 5, 0, 0], [0, 8, 0, 9, 0, 0, 1, 0, 2], [1, 0, 0, 0, 0, 0, 0, 0, 0], [0, 7, 9, 0, 8, 0, 2, 0, 5], [0, 0, 1, 0, 0, 0, 0, 0, 0], [0, 0, 3, 0, 2, 1, 9, 0, 0], [9, 6, 0, 0, 0, 0, 0, 5, 0], [2, 0, 0, 0, 0, 7, 4, 6, 0], [3, 0, 0, 1, 6, 5, 0, 0, 0]], "clues": 30, "id": 6908754781950316884}, {"puzzle": [[0, 0, 0, 0, 0, 0, 1, 0, 0], [0, 0, 9, 3, 0, 4, 7, 0, 0], [0, 7, 0, 0, 0, 2, 5, 9, 0], [0, 0, 3, 0, 5, 0, 0, 4, 6], [0, 6, 0, 4, 2, 3, 0, 1, 0], [0, 2, 0, 0, 6, 0, 0, 0, 5], [6, 0, 0, 2, 0, 0, 0, 0, 7], [0, 4, 5, 0, 0, 0, 6, 0, 0], [0, 0, 2, 5, 0, 6, 0, 0, 0]], "clues": 30, "id": 36552434919210043}, {"puzzle": [[0, 1, 0, 0, 0, 2, 0, 5, 0], [0, 5, 9, 1, 0, 0, 0, 3, 0], [0, 0, 2, 5, 9, 0, 1, 0, 0], [0, 0, 5, 0, 0, 0, 8, 2, 1], [1, 0, 0, 2, 0, 5, 0, 0, 9], [0, 0, 0, 9, 0, 0, 0, 0, 5], [0, 0, 1, 0, 4, 0, 5, 0, 0], [5, 4, 0, 0, 0, 9, 0, 0, 0], [6, 8, 0, 0, 0, 0, 0, 9, 0]], "clues": 30, "id": 1897634440170873529}, {"puzzle": [[0, 0, 0, 9, 0, 5, 0, 8, 0], [3, 6, 0, 0, 0, 0, 0, 5, 9], [9, 0, 5, 0, 6, 0, 4, 0, 0], [1, 0, 0, 0, 9, 0, 0, 0, 8], [0, 0, 0, 7, 8, 3, 0, 0, 0], [8, 0, 9, 0, 0, 0, 3, 0, 4], [0, 0, 0, 0, 1, 0, 0, 3, 0], [0, 3, 0, 0, 0, 0, 8, 4, 0], [0, 8, 0, 2, 0, 4, 0, 0, 6]], "clues": 30, "id": -5997515120798910964}, {"puzzle": [[0, 5, 6, 0, 3, 0, 1, 0, 7], [0, 3, 0, 0, 0, 0, 0, 5, 0], [8, 0, 0, 0, 0, 5, 3, 0, 9], [1, 0, 3, 8, 0, 0, 0, 0, 0], [0, 0, 0, 4, 0, 9, 0, 0, 0], [7, 0, 8, 0, 0, 6, 0, 0, 0], [3, 0, 0, 0, 0, 0, 0, 7, 4], [0, 2, 0, 7, 0, 0, 0, 6, 0], [0, 0, 4, 9, 8, 0, 5, 0, 3]], "clues": 30, "id": 8318013246428289755}, {"puzzle": [[0, 0, 7, 0, 2, 0, 0, 9, 0], [0, 0, 0, 0, 0, 6, 2, 8, 0], [2, 0, 0, 3, 0, 0, 5, 0, 4], [1, 3, 0, 0, 0, 0, 0, 0, 6], [0, 0, 0, 9, 4, 3, 0, 0, 0], [8, 0, 0, 0, 6, 0, 0, 0, 3], [0, 2, 0, 8, 0, 0, 6, 4, 0], [0, 0, 6, 0, 0, 4, 0, 1, 0], [0, 1, 0, 0, 5, 9, 7, 0, 0]], "clues": 30, "id": 8844774914235752084}, {"puzzle": [[0, 3, 0, 0, 0, 0, 1, 0, 2], [0, 1, 0, 5, 9, 0, 0, 7, 0], [0, 0, 0, 3, 0, 1, 8, 0, 0], [0, 0, 0, 0, 0, 7, 0, 1, 5], [0, 0, 3, 0, 1, 0, 2, 0, 0], [0, 7, 2, 0, 4, 5, 0, 0, 0], [0, 0, 0, 0, 0, 0, 6, 9, 0], [5, 0, 0, 9, 8, 0, 7, 0, 0], [0, 0, 0, 7, 0, 6, 0, 4, 1]], "clues": 30, "id": -3796563514427540181}, {"puzzle": [[1, 5, 0, 0, 0, 0, 9, 0, 3], [0, 0, 0, 1, 0, 4, 0, 0, 0], [0, 0, 6, 0, 3, 0, 1, 0, 8], [0, 6, 5, 0, 7, 0, 2, 0, 0], [0, 3, 0, 0, 4, 8, 0, 5, 0], [0, 0, 0, 0, 5, 6, 0, 3, 1], [6, 0, 0, 4, 0, 3, 0, 0, 0], [3, 0, 0, 0, 0, 0, 0, 0, 2], [5, 2, 0, 0, 0, 0, 3, 0, 7]], "clues": 31, "id": 7552869684874907371}, {"puzzle": [[0, 2, 0, 0, 0, 6, 0, 0, 0], [6, 0, 8, 9, 0, 0, 5, 0, 0], [0, 0, 0, 0, 0, 0, 8, 2, 0], [0, 3, 0, 1, 7, 0, 0, 0, 0], [0, 0, 0, 0, 6, 3, 0, 5, 0], [5, 0, 4, 0, 9, 0, 3, 7, 0], [0, 8, 0, 0, 0, 0, 7, 0, 0], [0, 5, 6, 7, 0, 0, 1, 8, 0], [4, 0, 0, 8, 0, 1, 0, 0, 2]], "clues": 30, "id": 377689138085343452}, {"puzzle": [[4, 0, 0, 5, 0, 0, 0, 2, 0], [0, 0, 0, 0, 0, 4, 0, 0, 0], [0, 0, 6, 0, 8, 2, 0, 0, 4], [3, 0, 0, 6, 0, 7, 0, 0, 0], [5, 6, 4, 0, 0, 0, 2, 0, 7], [0, 0, 8, 2, 0, 5, 6, 0, 0], [0, 3, 0, 4, 0, 0, 0, 6, 9], [0, 0, 0, 0, 0, 8, 0, 7, 2], [0, 2, 0, 9, 7, 0, 0, 0, 5]], "clues": 31, "id": 2466370918720007726}, {"puzzle": [[0, 9, 0, 0, 6, 0, 0, 5, 0], [0, 4, 0, 5, 0, 9, 0, 0, 0], [0, 0, 0, 7, 4, 0, 0, 1, 0], [9, 0, 0, 2, 0, 8, 0, 0, 0], [0, 7, 0, 0, 3, 0, 5, 0, 2], [0, 0, 0, 0, 0, 0, 7, 0, 8], [0, 0, 7, 0, 0, 4, 9, 0, 0], [4, 0, 0, 3, 0, 7, 0, 8, 5], [0, 1, 0, 0, 2, 5, 0, 7, 0]], "clues": 30, "id": 3525219787097895631}, {"puzzle": [[9, 0, 0, 0, 0, 0, 0, 0, 7], [3, 1, 0, 9, 0, 0, 0, 0, 0], [0, 5, 0, 0, 1, 0, 3, 4, 0], [0, 0, 8, 0, 0, 5, 0, 7, 0], [0, 0, 0, 1, 2, 3, 0, 5, 0], [4, 2, 0, 0, 0, 6, 9, 0, 3], [5, 6, 3, 0, 8, 0, 0, 9, 0], [0, 0, 0, 3, 0, 9, 0, 0, 0], [0, 0, 2, 0, 4, 0, 5, 0, 0]], "clues": 31, "id": 6661629288133785591}, {"puzzle": [[4, 0, 0, 0, 0, 0, 6, 0, 0], [0, 0, 0, 0, 0, 7, 0, 0, 0], [0, 5, 0, 2, 3, 0, 9, 7, 0], [0, 3, 0, 0, 2, 1, 0, 9, 0], [9, 0, 5, 0, 8, 0, 0, 0, 6], [0, 0, 4, 5, 9, 0, 0, 0, 3], [0, 4, 0, 9, 6, 0, 0, 5, 0], [5, 0, 9, 0, 0, 8, 4, 0, 2], [0, 0, 0, 0, 0, 0, 3, 0, 9]], "clues": 31, "id": -5070497625406705363}, {"puzzle": [[7, 2, 0, 0, 1, 0, 0, 0, 4], [0, 0, 9, 0, 0, 0, 7, 0, 0], [0, 4, 0, 7, 0, 9, 0, 0, 2], [9, 0, 0, 0, 4, 0, 0, 7, 3], [0, 0, 3, 0, 0, 0, 5, 0, 0], [0, 0, 0, 0, 5, 3, 1, 4, 0], [0, 0, 0, 1, 3, 8, 0, 0, 0], [8, 0, 2, 0, 0, 0, 4, 3, 0], [3, 0, 0, 0, 0, 6, 0, 1, 7]], "clues": 31, "id": 6963044356721907276}, {"puzzle": [[0, 0, 0, 0, 0, 0, 0, 5, 0], [0, 5, 0, 0, 0, 0, 4, 0, 0], [0, 3, 0, 0, 4, 1, 0, 0, 9], [1, 0, 0, 0, 9, 0, 5, 3, 0], [8, 0, 0, 3, 0, 0, 0, 0, 6], [3, 0, 4, 2, 8, 0, 0, 0, 0], [0, 0, 2, 0, 7, 8, 3, 0, 0], [0, 0, 0, 0, 0, 2, 1, 8, 0], [9, 0, 0, 1, 0, 4, 0, 2, 7]], "clues": 30, "id": 8561557420932486991}, {"puzzle": [[3, 0, 2, 8, 0, 0, 6, 0, 0], [4, 0, 0, 0, 6, 3, 0, 5, 0], [0, 0, 0, 5, 1, 0, 0, 0, 2], [0, 0, 6, 0, 0, 0, 1, 0, 0], [0, 8, 4, 0, 0, 0, 9, 7, 0], [0, 0, 9, 1, 0, 8, 4, 6, 0], [8, 0, 0, 0, 9, 6, 0, 0, 0], [0, 1, 0, 4, 5, 0, 0, 0, 0], [6, 0, 0, 0, 0, 1, 0, 3, 0]], "clues": 31, "id": -5066659439159597961}, {"puzzle": [[2, 0, 4, 8, 0, 7, 0, 0, 0], [0, 0, 3, 0, 0, 0, 0, 0, 4], [0, 0, 0, 0, 5, 4, 0, 0, 0], [8, 7, 0, 0, 0, 0, 0, 4, 5], [0, 0, 0, 2, 4, 3, 0, 0, 0], [4, 3, 0, 0, 0, 0, 6, 0, 2], [9, 0, 0, 7, 6, 0, 5, 0, 0], [0, 2, 6, 3, 0, 5, 0, 8, 0], [0, 0, 7, 0, 0, 0, 0, 9, 6]], "clues": 31, "id": -3984699324983700150}, {"puzzle": [[0, 2, 0, 0, 7, 5, 0, 0, 0], [0, 0, 9, 0, 0, 0, 0, 7, 1], [4, 7, 0, 0, 1, 0, 0, 8, 0], [8, 0, 0, 0, 0, 0, 0, 0, 3], [0, 6, 4, 0, 3, 0, 0, 5, 0], [5, 0, 3, 8, 0, 0, 2, 0, 7], [0, 0, 0, 0, 5, 0, 0, 0, 0], [0, 0, 1, 6, 0, 3, 0, 0, 5], [0, 0, 0, 4, 8, 0, 1, 9, 0]], "clues": 30, "id": -8265154656363498393}, {"puzzle": [[1, 0, 4, 0, 0, 0, 8, 0, 0], [6, 0, 5, 0, 0, 0, 0, 0, 0], [0, 0, 0, 4, 0, 2, 0, 7, 6], [0, 0, 0, 0, 4, 0, 9, 2, 3], [4, 0, 0, 0, 2, 0, 0, 0, 1], [0, 0, 3, 0, 9, 0, 0, 4, 0], [0, 1, 0, 9, 0, 4, 0, 0, 0], [0, 8, 0, 0, 0, 5, 2, 9, 0], [7, 0, 9, 2, 8, 0, 6, 0, 0]], "clues": 31, "id": -1524274794676518074}, {"puzzle": [[0, 7, 0, 0, 9, 0, 0, 4, 0], [3, 0, 0, 0, 0, 0, 2, 0, 0], [0, 0, 0, 0, 0, 6, 0, 5, 0], [0, 0, 7, 3, 5, 4, 0, 0, 0], [0, 5, 0, 0, 8, 0, 0, 1, 0], [0, 0, 8, 0, 6, 0, 0, 0, 5], [0, 0, 6, 0, 0, 5, 0, 3, 1], [0, 2, 4, 0, 0, 0, 0, 9, 6], [8, 0, 5, 6, 1, 9, 0, 0, 0]], "clues": 30, "id": -4872822997501038795}, {"puzzle": [[0, 0, 5, 0, 0, 7, 0, 0, 0], [1, 0, 0, 0, 0, 0, 0, 8, 6], [6, 0, 2, 8, 0, 0, 7, 0, 5], [8, 5, 0, 6, 0, 0, 0, 0, 7], [0, 0, 6, 0, 2, 0, 3, 0, 0], [0, 2, 0, 0, 7, 1, 0, 0, 0], [0, 0, 1, 0, 9, 0, 8, 0, 0], [2, 0, 0, 1, 0, 0, 0, 5, 4], [0, 0, 0, 0, 0, 6, 1, 9, 0]], "clues": 30, "id": 724222649001614136}, {"puzzle": [[0, 2, 0, 5, 0, 0, 3, 0, 0], [0, 0, 0, 3, 2, 0, 0, 0, 8], [0, 0, 0, 0, 9, 8, 0, 2, 0], [2, 0, 0, 0, 0, 0, 0, 0, 0], [0, 0, 6, 0, 0, 0, 9, 0, 2], [9, 3, 0, 0, 0, 2, 8, 7, 0], [0, 0, 0, 8, 1, 0, 0, 6, 0], [0, 0, 7, 2, 0, 0, 5, 3, 1], [4, 5, 0, 0, 0, 6, 2, 0, 0]], "clues": 30, "id": 2155539387214859394}, {"puzzle": [[2, 6, 0, 0, 0, 0, 0, 0, 3], [0, 0, 0, 9, 6, 0, 2, 7, 0], [0, 0, 4, 0, 0, 0, 9, 0, 0], [0, 0, 1, 0, 5, 6, 0, 0, 0], [0, 3, 0, 2, 0, 9, 0, 8, 0], [8, 2, 0, 4, 0, 0, 0, 0, 1], [0, 0, 6, 1, 0, 0, 8, 5, 0], [0, 0, 0, 0, 9, 5, 0, 3, 2], [9, 0, 2, 0, 0, 0, 0, 0, 6]], "clues": 31, "id": -3037421828021944969}, {"puzzle": [[0, 3, 0, 8, 0, 7, 0, 2, 0], [0, 0, 0, 9, 4, 0, 0, 0, 0], [6, 0, 9, 0, 0, 0, 7, 0, 8], [5, 9, 0, 7, 0, 1, 0, 0, 0], [0, 4, 0, 0, 5, 0, 0, 7, 3], [0, 0, 1, 0, 3, 0, 5, 0, 0], [0, 0, 7, 0, 6, 0, 4, 0, 0], [0, 5, 0, 0, 9, 0, 0, 0, 0], [0, 8, 0, 3, 0, 5, 0, 9, 0]], "clues": 30, "id": -5973608918528837947}, {"puzzle": [[3, 7, 0, 0, 0, 0, 0, 0, 0], [0, 5, 0, 0, 6, 4, 0, 0, 1], [0, 0, 0, 0, 0, 0, 5, 2, 0], [0, 0, 4, 2, 0, 0, 3, 0, 9], [6, 2, 0, 0, 0, 0, 0, 0, 8], [0, 0, 5, 0, 0, 8, 2, 6, 0], [0, 0, 2, 5, 0, 7, 0, 0, 3], [0, 0, 0, 6, 2, 0, 4, 0, 5], [5, 0, 6, 0, 0, 0, 1, 7, 0]], "clues": 31, "id": -5892341726768959133}, {"puzzle": [[0, 8, 0, 9, 7, 0, 0, 0, 0], [0, 0, 0, 0, 0, 0, 8, 1, 3], [0, 0, 0, 0, 8, 4, 0, 0, 0], [0, 0, 0, 0, 0, 3, 1, 8, 0], [8, 0, 0, 5, 1, 0, 0, 0, 4], [1, 0, 3, 8, 0, 0, 0, 7, 0], [4, 2, 0, 1, 0, 0, 0, 0, 0], [0, 0, 0, 0, 0, 7, 3, 2, 1], [0, 0, 1, 0, 6, 8, 0, 0, 9]], "clues": 30, "id": 1062269041104472179}, {"puzzle": [[0, 1, 0, 5, 7, 0, 2, 0, 0], [0, 0, 0, 3, 8, 2, 1, 0, 0], [7, 2, 5, 0, 0, 0, 0, 0, 8], [0, 0, 0, 0, 0, 0, 6, 0, 0], [1, 0, 0, 0, 0, 7, 0, 8, 3], [0, 5, 8, 1, 0, 0, 0, 2, 0], [0, 0, 1, 0, 0, 0, 0, 6, 0], [0, 0, 0, 7, 0, 8, 9, 0, 0], [0, 0, 6, 0, 1, 9, 0, 3, 0]], "clues": 30, "id": 8554348357184053376}, {"puzzle": [[0, 0, 6, 0, 8, 0, 7, 2, 0], [0, 5, 7, 0, 0, 0, 0, 9, 8], [0, 0, 0, 7, 5, 0, 0, 3, 0], [5, 0, 0, 0, 7, 0, 6, 0, 0], [7, 0, 0, 0, 0, 0, 5, 0, 3], [9, 0, 0, 0, 4, 0, 8, 0, 0], [0, 0, 0, 0, 0, 8, 0, 5, 0], [0, 0, 9, 4, 0, 5, 0, 0, 7], [4, 0, 5, 3, 0, 0, 9, 0, 0]], "clues": 30, "id": -4560851392045341896}],
	"hard": [{"puzzle": [[0, 0, 5, 0, 0, 0, 7, 4, 0], [3, 0, 0, 6, 0, 0, 0, 1, 9], [0, 0, 0, 0, 0, 1, 0, 0, 5], [0, 0, 0, 7, 0, 0, 0, 2, 0], [9, 0, 0, 0, 0, 5, 8, 0, 0], [7, 0, 0, 8, 4, 0, 0, 0, 0], [0, 0, 3, 0, 9, 0, 0, 0, 2], [0, 9, 0, 4, 0, 0, 0, 0, 0], [8, 0, 0, 0, 0, 0, 1, 0, 3]], "clues": 25, "id": -5330399042245753260}, {"puzzle": [[0, 4, 0, 1, 0, 0, 0, 0, 0], [0, 0, 0, 0, 0, 0, 0, 0, 0], [6, 5, 3, 0, 0, 0, 0, 0, 1], [0, 8, 0, 9, 0, 0, 7, 4, 0], [0, 0, 2, 4, 0, 0, 9, 1, 0], [0, 0, 0, 0, 0, 0, 2, 0, 8], [0, 0, 0, 5, 6, 2, 0, 0, 0], [0, 1, 0, 0, 7, 0, 0, 6, 0], [0, 0, 4, 0, 0, 1, 0, 0, 3]], "clues": 25, "id": 8377144854702904995}, {"puzzle": [[3, 8, 0, 1, 0, 0, 0, 0, 0], [0, 0, 0, 0, 5, 0, 6, 0, 0], [0, 0, 0, 9, 0, 0, 0, 0, 3], [0, 4, 0, 0, 0, 0, 0, 0, 0], [0, 0, 5, 0, 1, 8, 0, 0, 0], [0, 0, 0, 0, 9, 0, 5, 6, 1], [0, 6, 0, 0, 2, 4, 7, 8, 0], [8, 0, 0, 0, 0, 0, 0, 0, 6], [0, 0, 4, 0, 8, 0, 0, 2, 0]], "clues": 25, "id": 6668287986489089615}, {"puzzle": [[0, 0, 0, 0, 0, 4, 8, 0, 0], [7, 9, 0, 5, 8, 0, 0, 0, 0], [0, 0, 0, 0, 9, 0, 0, 0, 0], [0, 7, 5, 0, 0, 0, 0, 4, 0], [1, 0, 6, 2, 0, 0, 0, 0, 0], [0, 0, 0, 0, 0, 0, 0, 0, 7], [5, 1, 0, 3, 0, 0, 2, 0, 0], [0, 0, 4, 8, 0, 0, 0, 0, 1], [6, 0, 2, 4, 0, 0, 5, 0, 0]], "clues": 25, "id": 8435300935595019557}, {"puzzle": [[0, 0, 0, 6, 0, 0, 8, 0, 0], [0, 0, 3, 5, 0, 4, 0, 0, 0], [6, 5, 0, 0, 2, 1, 7, 0, 0], [0, 6, 0, 0, 0, 0, 0, 0, 0], [0, 0, 0, 0, 0, 0, 0, 5, 0], [0, 7, 1, 3, 8, 0, 0, 2, 0], [0, 0, 7, 0, 1, 0, 6, 0, 4], [0, 1, 0, 0, 0, 0, 0, 0, 0], [9, 0, 0, 0, 0, 3, 0, 0, 7]], "clues": 25, "id": -3657422926591067637}, {"puzzle": [[7, 0, 8, 2, 0, 0, 0, 6, 0], [0, 0, 4, 0, 0, 8, 0, 0, 9], [0, 0, 1, 0, 5, 0, 0, 0, 0], [0, 0, 0, 0, 0, 0, 0, 0, 2], [0, 0, 6, 0, 0, 1, 0, 4, 0], [3, 0, 0, 0, 0, 0, 6, 7, 0], [0, 4, 0, 1, 0, 0, 0, 0, 0], [0, 0, 0, 0, 4, 5, 0, 8, 7], [0, 0, 5, 0, 7, 0, 0, 0, 3]], "clues": 25, "id": -4676412631879803511}, {"puzzle": [[3, 0, 0, 0, 6, 0, 0, 4, 2], [0, 0, 0, 0, 0, 5, 0, 0, 0], [0, 6, 1, 0, 3, 0, 0, 0, 0], [0, 8, 0, 0, 0, 7, 0, 0, 6], [7, 0, 0, 0, 2, 0, 1, 0, 5], [0, 9, 0, 0, 0, 0, 3, 0, 0], [0, 0, 0, 0, 1, 3, 0, 0, 0], [5, 0, 0, 0, 0, 6, 0, 9, 3], [0, 0, 7, 4, 0, 0, 0, 0, 0]], "clues": 25, "id": 3875370107411511198}, {"puzzle": [[6, 0, 0, 0, 0, 0, 2, 0, 0], [0, 7, 1, 3, 0, 0, 0, 0, 0], [3, 9, 0, 4, 0, 0, 0, 7, 0], [0, 0, 3, 0, 0, 2, 8, 9, 0], [0, 1, 0, 0, 8, 0, 0, 0, 4], [0, 0, 0, 5, 0, 0, 1, 0, 0], [0, 6, 0, 0, 0, 8, 5, 4, 0], [0, 0, 0, 0, 0, 0, 0, 0, 1], [0, 0, 8, 2, 0, 0, 0, 0, 0]], "clues": 25, "id": -6605478653519175707}, {"puzzle": [[0, 0, 0, 0, 0, 8, 0, 0, 0], [2, 0, 3, 0, 0, 0, 4, 0, 6], [0, 0, 5, 4, 0, 3, 7, 0, 0], [0, 0, 4, 0, 0, 0, 6, 0, 0], [0, 9, 0, 8, 0, 0, 0, 0, 0], [5, 0, 0, 9, 0, 4, 0, 0, 2], [7, 0, 0, 5, 8, 9, 0, 0, 3], [4, 0, 0, 2, 0, 0, 0, 7, 0], [0, 0, 0, 0, 0, 0, 0, 0, 0]], "clues": 25, "id": 6736648352168101866}, {"puzzle": [[0, 4, 0, 0, 0, 8, 0, 0, 0], [0, 0, 6, 0, 2, 0, 0, 0, 0], [0, 0, 5, 7, 0, 0, 0, 0, 8], [0, 5, 2, 0, 0, 7, 0, 0, 0], [1, 0, 0, 3, 5, 0, 0, 0, 0], [4, 0, 0, 0, 0, 2, 7, 0, 0], [0, 7, 0, 9, 0, 0, 0, 6, 4], [0, 0, 0, 0, 0, 0, 0, 1, 0], [0, 0, 0, 4, 3, 1, 0, 0, 2]], "clues": 25, "id": -1970248820441760849}, {"puzzle": [[0, 0, 6, 0, 0, 0, 5, 1, 0], [0, 5, 2, 0, 7, 0, 0, 0, 0], [0, 0, 7, 6, 1, 0, 0, 0, 0], [0, 8, 0, 0, 0, 0, 0, 5, 0], [7, 0, 0, 0, 0, 2, 6, 9, 8], [0, 0, 4, 0, 0, 7, 0, 0, 0], [0, 0, 9, 2, 6, 0, 0, 0, 0], [0, 0, 0, 0, 9, 0, 3, 0, 0], [0, 0, 0, 0, 0, 0, 1, 6, 0]], "clues": 25, "id": 1372342925777135988}, {"puzzle": [[0, 0, 0, 8, 6, 0, 9, 0, 5], [0, 8, 0, 0, 0, 0, 0, 2, 1], [7, 0, 0, 0, 0, 4, 0, 0, 8], [6, 2, 0, 0, 0, 5, 4, 3, 0], [5, 0, 0, 0, 7, 0, 0, 0, 0], [0, 0, 0, 0, 4, 0, 6, 0, 0], [0, 0, 0, 0, 9, 2, 0, 8, 0], [0, 6, 1, 0, 0, 0, 5, 0, 0], [0, 0, 0, 0, 0, 0, 0, 0, 0]], "clues": 25, "id": 1852022848812928941}, {"puzzle": [[3, 0, 0, 0, 0, 5, 0, 7, 8], [0, 0, 0, 6, 0, 7, 0, 0, 0], [0, 6, 0, 0, 1, 0, 4, 0, 0], [6, 0, 0, 0, 0, 0, 3, 0, 7], [0, 0, 4, 9, 0, 0, 0, 6, 0], [0, 0, 0, 0, 0, 0, 0, 0, 4], [4, 2, 0, 0, 0, 0, 0, 0, 0], [0, 0, 0, 0, 0, 8, 0, 5, 1], [0, 1, 3, 0, 0, 6, 7, 0, 0]], "clues": 25, "id": 8604052131790381259}, {"puzzle": [[0, 8, 0, 0, 0, 0, 0, 9, 0], [0, 0, 5, 0, 8, 0, 7, 0, 0], [7, 0, 0, 0, 0, 9, 0, 0, 4], [0, 1, 6, 0, 4, 2, 0, 0, 0], [0, 3, 0, 0, 9, 0, 1, 0, 7], [8, 0, 0, 0, 3, 0, 0, 0, 0], [4, 0, 0, 0, 0, 0, 5, 0, 0], [0, 2, 0, 5, 0, 0, 0, 1, 0], [0, 0, 0, 0, 1, 0, 9, 0, 0]], "clues": 25, "id": 4666525994592325916}, {"puzzle": [[0, 0, 0, 9, 2, 0, 0, 0, 1], [0, 0, 0, 0, 5, 7, 0, 0, 0], [9, 0, 0, 3, 0, 6, 0, 4, 2], [0, 9, 2, 1, 7, 0, 0, 0, 4], [0, 3, 0, 0, 0, 0, 0, 0, 0], [0, 6, 0, 0, 0, 9, 0, 0, 0], [4, 0, 0, 0, 3, 0, 0, 0, 0], [6, 0, 0, 0, 0, 8, 0, 0, 0], [0, 2, 7, 0, 0, 0, 6, 0, 0]], "clues": 25, "id": 1865249344677470183}, {"puzzle": [[0, 0, 0, 2, 0, 1, 0, 3, 0], [0, 0, 1, 0, 0, 0, 4, 0, 0], [7, 0, 0, 0, 0, 0, 0, 9, 5], [0, 0, 0, 0, 4, 0, 9, 1, 0], [0, 0, 4, 3, 0, 7, 0, 0, 0], [1, 0, 6, 9, 0, 0, 0, 0, 0], [6, 0, 0, 0, 2, 0, 0, 0, 7], [0, 5, 0, 0, 0, 9, 0, 0, 0], [2, 0, 0, 6, 0, 0, 0, 5, 0]], "clues": 25, "id": -1420313703962123376}, {"puzzle": [[7, 0, 0, 0, 0, 1, 0, 0, 3], [0, 0, 5, 0, 2, 0, 9, 0, 0], [3, 0, 9, 0, 0, 0, 1, 7, 0], [0, 0, 0, 0, 0, 0, 0, 0, 0], [9, 6, 8, 0, 0, 2, 0, 0, 0], [0, 0, 0, 0, 0, 0, 6, 0, 8], [0, 0, 0, 0, 8, 3, 0, 1, 0], [0, 7, 0, 4, 0, 0, 0, 0, 0], [5, 8, 1, 0, 0, 0, 0, 9, 0]], "clues": 25, "id": 3101721194445728670}, {"puzzle": [[0, 9, 8, 0, 0, 0, 3, 0, 2], [0, 0, 7, 0, 9, 0, 0, 0, 0], [0, 6, 0, 3, 2, 0, 0, 7, 0], [0, 0, 0, 0, 0, 0, 0, 0, 0], [0, 0, 6, 0, 8, 9, 0, 0, 4], [8, 0, 0, 0, 0, 4, 0, 0, 0], [0, 8, 0, 6, 0, 0, 1, 5, 0], [0, 0, 1, 4, 0, 0, 7, 0, 0], [0, 0, 0, 0, 0, 7, 4, 0, 0]], "clues": 25, "id": -8747006418620632444}, {"puzzle": [[0, 0, 0, 0, 0, 0, 0, 0, 0], [6, 8, 0, 0, 0, 0, 0, 4, 9], [0, 0, 0, 0, 7, 0, 0, 0, 5], [1, 0, 8, 0, 0, 6, 0, 0, 0], [3, 6, 7, 9, 0, 0, 8, 0, 0], [0, 0, 0, 7, 0, 0, 0, 0, 0], [0, 4, 0, 8, 2, 0, 0, 3, 7], [7, 0, 5, 0, 1, 0, 0, 9, 0], [0, 0, 0, 0, 0, 0, 0, 2, 0]], "clues": 25, "id": -8022383238960630144}, {"puzzle": [[0, 4, 0, 0, 8, 0, 0, 0, 0], [0, 0, 0, 3, 0, 0, 0, 9, 7], [0, 3, 0, 0, 7, 0, 0, 5, 0], [5, 0, 2, 0, 4, 0, 7, 0, 8], [8, 0, 0, 0, 0, 0, 2, 0, 0], [0, 0, 0, 9, 0, 0, 0, 0, 0], [0, 0, 0, 0, 0, 4, 0, 0, 0], [6, 0, 7, 8, 0, 0, 9, 0, 0], [0, 0, 4, 7, 5, 0, 0, 0, 1]], "clues": 25, "id": 6668442303983393610}, {"puzzle": [[0, 2, 3, 4, 8, 0, 5, 0, 0], [0, 0, 0, 0, 0, 0, 3, 0, 9], [0, 0, 0, 5, 0, 0, 0, 4, 0], [6, 0, 0, 0, 1, 0, 2, 0, 0], [0, 8, 7, 0, 2, 0, 0, 0, 0], [0, 1, 0, 0, 3, 0, 0, 5, 0], [0, 0, 0, 0, 0, 0, 0, 6, 0], [0, 0, 8, 2, 0, 0, 1, 0, 4], [0, 3, 0, 0, 9, 0, 0, 0, 0]], "clues": 25, "id": -4629439276148245467}, {"puzzle": [[6, 0, 0, 1, 0, 0, 2, 0, 0], [0, 0, 1, 0, 9, 0, 0, 0, 0], [0, 0, 8, 0, 0, 0, 6, 0, 0], [2, 7, 0, 6, 0, 0, 0, 0, 0], [0, 0, 0, 0, 4, 7, 0, 0, 6], [0, 0, 0, 9, 5, 0, 8, 0, 0], [1, 5, 0, 0, 3, 0, 4, 0, 0], [0, 6, 0, 0, 0, 9, 0, 0, 0], [0, 3, 0, 0, 0, 0, 5, 0, 7]], "clues": 25, "id": -6336211764880642842}, {"puzzle": [[0, 0, 0, 9, 1, 0, 0, 0, 0], [0, 0, 9, 3, 0, 4, 5, 8, 0], [5, 0, 0, 0, 0, 0, 0, 0, 1], [0, 0, 7, 1, 0, 3, 0, 0, 0], [0, 0, 5, 0, 9, 0, 0, 0, 6], [0, 0, 0, 4, 8, 0, 0, 3, 0], [0, 0, 0, 2, 0, 0, 8, 4, 0], [1, 0, 3, 0, 0, 0, 0, 6, 0], [0, 0, 0, 0, 0, 8, 0, 0, 0]], "clues": 25, "id": 4525526468429984643}, {"puzzle": [[0, 8, 0, 0, 0, 0, 0, 7, 4], [0, 0, 0, 1, 0, 5, 0, 3, 0], [0, 6, 0, 0, 4, 0, 8, 0, 0], [4, 0, 7, 0, 0, 3, 0, 0, 0], [9, 0, 0, 0, 6, 0, 0, 0, 8], [0, 1, 8, 0, 0, 7, 0, 0, 0], [0, 0, 0, 0, 0, 6, 1, 0, 0], [0, 3, 0, 0, 0, 1, 6, 0, 0], [0, 4, 0, 0, 5, 0, 0, 0, 0]], "clues": 25, "id": 607675449302471315}, {"puzzle": [[0, 0, 0, 0, 0, 2, 0, 8, 0], [0, 4, 0, 1, 5, 0, 0, 0, 0], [0, 0, 0, 0, 0, 6, 3, 0, 5], [0, 3, 0, 0, 0, 9, 1, 0, 0], [7, 0, 4, 0, 3, 0, 0, 0, 9], [0, 0, 0, 0, 4, 1, 0, 2, 0], [0, 0, 0, 0, 0, 7, 0, 0, 0], [8, 0, 0, 0, 1, 0, 0, 3, 0], [1, 0, 0, 0, 0, 0, 6, 7, 0]], "clues": 25, "id": -2475694037915269156}, {"puzzle": [[6, 0, 0, 3, 4, 0, 5, 0, 0], [0, 0, 9, 0, 5, 0, 4, 0, 8], [0, 0, 0, 0, 8, 0, 0, 0, 0], [0, 6, 1, 0, 0, 0, 7, 4, 0], [0, 0, 0, 4, 0, 0, 3, 0, 0], [0, 0, 0, 0, 0, 6, 0, 2, 0], [1, 0, 0, 0, 6, 0, 0, 5, 0], [8, 0, 4, 0, 0, 0, 0, 0, 7], [7, 0, 0, 0, 0, 1, 0, 0, 0]], "clues": 25, "id": 3025905874082997374}, {"puzzle": [[0, 0, 2, 4, 0, 0, 8, 3, 0], [0, 0, 0, 0, 7, 0, 0, 0, 0], [5, 0, 8, 3, 0, 0, 7, 0, 9], [8, 0, 0, 0, 0, 0, 0, 0, 0], [0, 2, 3, 0, 0, 0, 1, 5, 0], [4, 9, 0, 0, 2, 0, 0, 0, 0], [0, 0, 7, 0, 1, 0, 0, 0, 0], [0, 0, 0, 2, 0, 5, 0, 0, 6], [0, 0, 4, 0, 0, 0, 2, 0, 0]], "clues": 25, "id": 1466798414036449605}, {"puzzle": [[0, 6, 0, 3, 0, 2, 1, 0, 0], [0, 0, 4, 7, 0, 0, 0, 0, 3], [7, 0, 0, 0, 0, 0, 0, 8, 0], [2, 0, 0, 5, 0, 0, 0, 0, 0], [0, 1, 0, 0, 0, 0, 0, 7, 6], [0, 0, 0, 0, 1, 0, 9, 0, 0], [0, 0, 0, 0, 0, 3, 7, 9, 0], [0, 0, 8, 0, 0, 0, 0, 0, 4], [4, 0, 0, 6, 0, 8, 0, 2, 0]], "clues": 25, "id": 8755626704260514499}, {"puzzle": [[1, 0, 0, 8, 3, 0, 0, 0, 5], [0, 5, 4, 0, 0, 0, 0, 0, 0], [0, 6, 0, 0, 0, 0, 0, 3, 0], [0, 1, 2, 9, 0, 0, 6, 0, 0], [6, 0, 0, 4, 0, 0, 0, 0, 9], [0, 0, 0, 3, 0, 2, 0, 0, 7], [4, 8, 0, 2, 0, 0, 0, 0, 0], [0, 0, 0, 0, 1, 0, 0, 0, 0], [0, 2, 9, 0, 0, 5, 0, 0, 0]], "clues": 25, "id": 312869053645768515}, {"puzzle": [[8, 0, 0, 2, 0, 0, 0, 0, 0], [0, 0, 0, 0, 0, 6, 0, 7, 0], [0, 0, 3, 0, 9, 0, 5, 0, 0], [0, 0, 0, 0, 0, 0, 0, 0, 0], [0, 9, 5, 4, 0, 0, 0, 2, 0], [3, 8, 0, 5, 0, 7, 9, 0, 0], [7, 0, 0, 0, 0, 0, 2, 6, 4], [1, 0, 0, 0, 0, 0, 0, 3, 0], [0, 0, 0, 0, 0, 8, 7, 9, 0]], "clues": 25, "id": -4536757254106911161}, {"puzzle": [[9, 0, 0, 0, 5, 0, 0, 1, 0], [0, 0, 0, 3, 0, 0, 9, 0, 0], [0, 4, 0, 0, 0, 8, 0, 0, 6], [0, 0, 8, 9, 6, 5, 0, 0, 0], [0, 0, 0, 0, 0, 0, 3, 0, 0], [0, 0, 5, 1, 0, 0, 0, 8, 0], [0, 0, 0, 0, 1, 0, 0, 7, 0], [6, 1, 0, 0, 0, 0, 0, 2, 0], [7, 0, 0, 0, 3, 4, 0, 0, 9]], "clues": 25, "id": 755872096172739178}, {"puzzle": [[0, 0, 0, 0, 0, 0, 5, 0, 0], [0, 4, 7, 0, 0, 0, 8, 0, 2], [0, 8, 0, 0, 0, 9, 0, 1, 0], [0, 0, 0, 0, 0, 5, 2, 9, 7], [7, 0, 0, 0, 3, 0, 0, 0, 1], [0, 1, 0, 4, 8, 0, 0, 5, 0], [0, 0, 6, 0, 0, 3, 0, 0, 0], [8, 9, 4, 0, 0, 0, 0, 0, 0], [0, 0, 0, 0, 0, 0, 9, 0, 0]], "clues": 25, "id": 3036582974715183185}, {"puzzle": [[0, 0, 5, 0, 2, 4, 3, 0, 0], [0, 8, 0, 0, 1, 0, 0, 0, 0], [2, 0, 3, 0, 0, 0, 9, 5, 0], [0, 0, 0, 0, 0, 0, 0, 2, 0], [0, 0, 0, 0, 4, 0, 6, 0, 7], [0, 0, 0, 8, 0, 3, 5, 9, 0], [0, 0, 0, 4, 0, 2, 0, 1, 0], [0, 0, 9, 0, 0, 7, 0, 0, 0], [0, 0, 0, 0, 5, 0, 4, 0, 0]], "clues": 25, "id": -8006743372017535860}, {"puzzle": [[0, 0, 0, 0, 7, 0, 2, 4, 0], [0, 0, 9, 5, 0, 0, 0, 0, 0], [0, 0, 2, 0, 0, 0, 0, 0, 5], [9, 7, 0, 0, 5, 2, 4, 0, 0], [0, 6, 0, 3, 0, 0, 0, 0, 0], [8, 2, 0, 6, 0, 0, 0, 7, 0], [0, 1, 0, 0, 3, 8, 0, 6, 0], [0, 0, 0, 0, 0, 0, 0, 0, 0], [6, 0, 0, 1, 0, 0, 7, 0, 0]], "clues": 25, "id": -1971383417222156213}, {"puzzle": [[0, 0, 0, 0, 2, 0, 3, 0, 0], [4, 0, 3, 0, 9, 0, 0, 0, 7], [0, 0, 0, 0, 0, 6, 9, 0, 4], [0, 3, 0, 0, 0, 9, 0, 6, 2], [2, 1, 4, 0, 0, 0, 8, 0, 0], [0, 8, 0, 0, 0, 3, 0, 0, 0], [0, 0, 0, 0, 0, 0, 0, 1, 0], [8, 0, 0, 0, 6, 0, 0, 0, 0], [1, 0, 0, 8, 0, 4, 0, 0, 0]], "clues": 25, "id": 9090025002248891883}, {"puzzle": [[0, 0, 0, 0, 9, 0, 0, 5, 4], [0, 3, 0, 0, 0, 4, 0, 8, 0], [0, 0, 0, 7, 2, 0, 0, 0, 3], [0, 0, 3, 0, 0, 0, 6, 0, 9], [0, 0, 0, 0, 0, 0, 0, 0, 0], [0, 7, 2, 0, 0, 0, 0, 0, 5], [1, 0, 0, 0, 0, 8, 0, 0, 0], [0, 0, 0, 2, 0, 1, 0, 0, 8], [0, 4, 6, 9, 5, 0, 0, 1, 0]], "clues": 25, "id": 2221949252610346484}, {"puzzle": [[0, 8, 2, 6, 4, 0, 9, 1, 0], [4, 0, 0, 0, 0, 0, 0, 0, 5], [0, 0, 0, 8, 1, 0, 0, 0, 6], [0, 5, 6, 4, 0, 0, 0, 0, 8], [0, 0, 0, 0, 0, 0, 0, 0, 7], [3, 2, 0, 0, 8, 0, 0, 4, 0], [0, 0, 0, 0, 0, 0, 0, 5, 0], [0, 0, 0, 0, 7, 6, 0, 0, 0], [0, 0, 0, 3, 0, 0, 0, 0, 4]], "clues": 25, "id": 5236791937972974074}, {"puzzle": [[0, 0, 0, 0, 3, 0, 5, 0, 0], [0, 0, 0, 0, 0, 0, 0, 0, 7], [0, 0, 0, 7, 9, 1, 0, 2, 0], [1, 0, 0, 0, 0, 0, 6, 0, 8], [8, 0, 0, 0, 0, 3, 9, 0, 0], [0, 9, 0, 5, 0, 0, 2, 4, 0], [0, 0, 9, 0, 4, 6, 0, 8, 0], [0, 1, 0, 0, 0, 0, 0, 0, 0], [0, 0, 0, 2, 0, 0, 4, 9, 0]], "clues": 25, "id": -639373553876767380}, {"puzzle": [[0, 0, 1, 0, 0, 0, 0, 3, 8], [0, 0, 0, 0, 5, 7, 0, 0, 0], [0, 6, 0, 0, 0, 0, 0, 0, 0], [5, 0, 0, 1, 0, 8, 6, 0, 0], [0, 0, 9, 0, 6, 0, 8, 0, 0], [0, 0, 8, 5, 4, 0, 0, 7, 0], [0, 0, 5, 0, 0, 1, 4, 0, 0], [0, 3, 0, 0, 0, 0, 0, 1, 0], [0, 0, 7, 0, 3, 0, 0, 5, 0]], "clues": 25, "id": 6040387024328927068}, {"puzzle": [[2, 0, 0, 0, 5, 6, 1, 0, 0], [0, 7, 0, 0, 0, 8, 0, 0, 0], [6, 0, 0, 0, 0, 4, 0, 0, 0], [0, 5, 6, 0, 0, 7, 0, 2, 0], [0, 9, 0, 8, 0, 5, 0, 4, 0], [0, 0, 7, 0, 3, 0, 0, 0, 0], [1, 0, 8, 0, 0, 0, 0, 9, 4], [0, 0, 5, 0, 0, 0, 0, 0, 8], [0, 0, 0, 0, 0, 0, 0, 0, 1]], "clues": 25, "id": 1932613221976036251}, {"puzzle": [[7, 0, 0, 0, 0, 0, 0, 5, 8], [0, 0, 0, 6, 0, 0, 9, 2, 0], [0, 0, 0, 0, 0, 0, 0, 0, 0], [0, 6, 0, 0, 4, 5, 0, 0, 0], [4, 0, 0, 3, 9, 8, 0, 0, 6], [0, 8, 3, 0, 0, 0, 0, 0, 0], [0, 3, 0, 0, 0, 0, 2, 0, 0], [6, 4, 0, 0, 7, 0, 8, 0, 3], [0, 0, 0, 0, 0, 6, 5, 0, 0]], "clues": 25, "id": 5945328999414832203}, {"puzzle": [[0, 0, 0, 9, 0, 1, 0, 0, 6], [9, 0, 0, 0, 5, 6, 0, 0, 0], [1, 0, 6, 0, 7, 0, 5, 0, 0], [0, 7, 0, 8, 0, 0, 3, 0, 0], [8, 2, 0, 0, 0, 0, 0, 5, 0], [0, 0, 1, 0, 0, 5, 0, 0, 0], [0, 0, 0, 7, 0, 4, 1, 8, 0], [6, 3, 0, 0, 0, 0, 2, 0, 0], [0, 0, 0, 0, 0, 0, 0, 0, 0]], "clues": 25, "id": -3659549162912667517}, {"puzzle": [[0, 0, 0, 0, 0, 2, 8, 4, 5], [1, 0, 0, 0, 8, 0, 0, 0, 0], [3, 0, 0, 0, 0, 0, 0, 0, 0], [0, 0, 7, 2, 1, 0, 0, 0, 0], [6, 0, 0, 7, 0, 0, 9, 0, 0], [0, 0, 5, 0, 0, 9, 0, 1, 3], [8, 1, 0, 0, 0, 6, 0, 0, 0], [0, 0, 9, 0, 7, 0, 0, 0, 8], [0, 0, 0, 0, 0, 0, 0, 3, 4]], "clues": 25, "id": 1029681908840917707}, {"puzzle": [[9, 0, 8, 0, 0, 3, 0, 0, 4], [1, 0, 0, 0, 0, 5, 0, 0, 0], [7, 5, 0, 0, 1, 4, 0, 0, 8], [0, 0, 3, 0, 4, 0, 0, 9, 0], [0, 0, 0, 0, 0, 0, 4, 0, 0], [0, 1, 0, 0, 8, 6, 0, 0, 0], [0, 0, 0, 7, 0, 0, 1, 0, 5], [0, 0, 9, 0, 0, 0, 0, 0, 7], [0, 0, 0, 0, 6, 0, 0, 4, 0]], "clues": 25, "id": -4788194820228946027}, {"puzzle": [[0, 0, 2, 0, 5, 4, 0, 3, 0], [0, 0, 0, 6, 1, 3, 5, 0, 0], [0, 7, 0, 0, 8, 0, 0, 0, 0], [0, 0, 1, 0, 0, 0, 0, 0, 0], [4, 3, 0, 0, 0, 0, 7, 0, 0], [0, 0, 0, 9, 0, 6, 8, 0, 3], [0, 5, 6, 8, 0, 0, 0, 0, 0], [8, 1, 0, 0, 0, 0, 0, 0, 6], [0, 0, 0, 0, 0, 2, 0, 0, 0]], "clues": 25, "id": -215042011128871039}, {"puzzle": [[0, 2, 0, 9, 0, 0, 0, 6, 3], [0, 0, 0, 0, 0, 3, 9, 0, 0], [0, 0, 6, 0, 8, 0, 0, 0, 0], [0, 8, 0, 0, 2, 0, 5, 0, 0], [0, 0, 0, 0, 9, 0, 1, 0, 6], [1, 0, 0, 7, 0, 0, 0, 3, 0], [0, 0, 1, 0, 0, 0, 6, 0, 9], [0, 0, 9, 0, 0, 4, 0, 8, 0], [5, 0, 0, 0, 0, 0, 0, 0, 2]], "clues": 25, "id": -2823003205800636186}, {"puzzle": [[0, 9, 0, 3, 0, 0, 0, 0, 6], [0, 0, 6, 0, 0, 1, 0, 3, 0], [1, 0, 0, 0, 0, 0, 5, 9, 0], [0, 6, 4, 0, 0, 0, 0, 0, 0], [0, 0, 0, 0, 0, 0, 2, 0, 0], [2, 0, 0, 4, 8, 3, 0, 0, 0], [0, 0, 7, 0, 0, 6, 0, 0, 5], [0, 0, 0, 0, 9, 0, 0, 7, 0], [9, 4, 0, 1, 0, 5, 0, 0, 0]], "clues": 25, "id": -798157456647885851}, {"puzzle": [[0, 0, 0, 3, 0, 6, 5, 0, 1], [0, 0, 0, 5, 0, 0, 0, 0, 6], [0, 0, 8, 9, 0, 0, 0, 2, 0], [0, 0, 0, 0, 0, 0, 7, 0, 0], [0, 0, 0, 8, 0, 0, 0, 0, 4], [2, 9, 6, 0, 1, 0, 0, 0, 0], [9, 0, 2, 0, 0, 0, 0, 0, 5], [0, 7, 0, 0, 3, 4, 6, 0, 0], [0, 3, 0, 1, 0, 0, 0, 0, 0]], "clues": 25, "id": -6725607927486858856}, {"puzzle": [[0, 0, 0, 0, 0, 0, 6, 0, 0], [0, 3, 0, 0, 0, 0, 4, 0, 8], [0, 0, 0, 0, 8, 7, 0, 0, 0], [4, 0, 2, 1, 0, 0, 0, 6, 0], [0, 7, 5, 9, 4, 6, 8, 0, 0], [0, 8, 0, 2, 0, 0, 0, 0, 0], [2, 0, 0, 0, 0, 0, 0, 0, 0], [5, 0, 0, 0, 0, 9, 7, 0, 3], [0, 0, 0, 0, 5, 0, 0, 0, 4]], "clues": 25, "id": 7957279794006841929}, {"puzzle": [[1, 4, 0, 0, 0, 2, 7, 3, 0], [8, 0, 0, 0, 4, 0, 0, 0, 0], [0, 0, 3, 8, 7, 6, 0, 0, 0], [0, 0, 0, 0, 0, 0, 3, 0, 0], [0, 0, 0, 4, 6, 8, 0, 0, 0], [0, 0, 0, 0, 9, 0, 5, 4, 0], [0, 0, 0, 0, 0, 0, 0, 0, 5], [5, 0, 0, 0, 2, 0, 6, 0, 0], [0, 7, 0, 0, 8, 1, 0, 0, 0]], "clues": 25, "id": -1979731555343800118}]
}